README.md
setup.py
tmessage/__init__.py
tmessage/auth.py
tmessage/cli.py
tmessage.egg-info/PKG-INFO
tmessage.egg-info/SOURCES.txt
tmessage.egg-info/dependency_links.txt
tmessage.egg-info/entry_points.txt
tmessage.egg-info/not-zip-safe
tmessage.egg-info/requires.txt
tmessage.egg-info/top_level.txt