Metadata-Version: 2.1
Name: tmessage
Version: 0.0.1
Summary: 
Home-page: https://github.com/Haider8/tmessage
Author: Haider Ali
Author-email: haider.lee23@gmail.com
License: GPL-3.0
Platform: UNKNOWN
Classifier: Programming Language :: Python :: 3
Classifier: Operating System :: OS Independent
Requires-Python: >=3.4
